__init__.py
plotting.py
preprocessing.py
analysis/__init__.py
analysis/evaluation.py
analysis/evaluation_util.py
analysis/perf_logger.py
build/lib/__init__.py
build/lib/plotting.py
build/lib/preprocessing.py
build/lib/analysis/__init__.py
build/lib/analysis/evaluation.py
build/lib/analysis/evaluation_util.py
build/lib/analysis/perf_logger.py
build/lib/build/lib/__init__.py
build/lib/build/lib/plotting.py
build/lib/build/lib/preprocessing.py
build/lib/build/lib/analysis/__init__.py
build/lib/build/lib/analysis/evaluation.py
build/lib/build/lib/analysis/evaluation_util.py
build/lib/build/lib/analysis/perf_logger.py
build/lib/build/lib/build/lib/__init__.py
build/lib/build/lib/build/lib/plotting.py
build/lib/build/lib/build/lib/preprocessing.py
build/lib/build/lib/build/lib/analysis/__init__.py
build/lib/build/lib/build/lib/analysis/evaluation.py
build/lib/build/lib/build/lib/analysis/evaluation_util.py
build/lib/build/lib/build/lib/analysis/perf_logger.py
build/lib/build/lib/build/lib/build/lib/__init__.py
build/lib/build/lib/build/lib/build/lib/plotting.py
build/lib/build/lib/build/lib/build/lib/preprocessing.py
build/lib/build/lib/build/lib/build/lib/analysis/__init__.py
build/lib/build/lib/build/lib/build/lib/analysis/evaluation.py
build/lib/build/lib/build/lib/build/lib/analysis/evaluation_util.py
build/lib/build/lib/build/lib/build/lib/analysis/perf_logger.py
build/lib/build/lib/build/lib/build/lib/build/lib/__init__.py
build/lib/build/lib/build/lib/build/lib/build/lib/plotting.py
build/lib/build/lib/build/lib/build/lib/build/lib/preprocessing.py
build/lib/build/lib/build/lib/build/lib/build/lib/analysis/__init__.py
build/lib/build/lib/build/lib/build/lib/build/lib/analysis/evaluation.py
build/lib/build/lib/build/lib/build/lib/build/lib/analysis/evaluation_util.py
build/lib/build/lib/build/lib/build/lib/build/lib/analysis/perf_logger.py
build/lib/build/lib/build/lib/build/lib/build/lib/build/lib/__init__.py
velovae-0.1.3.dist-info/LICENSE
velovae-0.1.3.dist-info/METADATA
velovae-0.1.3.dist-info/WHEEL
velovae-0.1.3.dist-info/top_level.txt
velovae-0.1.3.dist-info/RECORD
