Metadata-Version: 2.1
Name: velovae
Version: 0.1.3
Summary: Bayesian Inference of RNA Velocity
Home-page: https://github.com/welch-lab/VeloVAE
Author: Yichen Gu
Author-email: gyichen@umich.edu
License: BSD 3-Clause License
Keywords: RNA velocity,single-cell RNA,variational autoencoder,deep generative Model,bayesian inference,ordinary differential equation
Classifier: Development Status :: 4 - Beta
Classifier: Intended Audience :: Science/Research
Classifier: License :: OSI Approved :: BSD License
Classifier: Natural Language :: English
Classifier: Operating System :: MacOS :: MacOS X
Classifier: Operating System :: Microsoft :: Windows
Classifier: Operating System :: POSIX :: Linux
Classifier: Programming Language :: Python :: 3
Classifier: Programming Language :: Python :: 3.7
Classifier: Programming Language :: Python :: 3.8
Classifier: Programming Language :: Python :: 3.9
Classifier: Topic :: Scientific/Engineering :: Bio-Informatics
Classifier: Topic :: Scientific/Engineering :: Visualization
License-File: LICENSE
Requires-Dist: torch >=1.8.0
Requires-Dist: anndata >=0.8.0
Requires-Dist: scanpy >=1.5
Requires-Dist: scvelo >=0.2.3
Requires-Dist: umap-learn >=0.3.10
Requires-Dist: numba >=0.41.0
Requires-Dist: numpy >=1.17
Requires-Dist: scipy >=1.4.1
Requires-Dist: pandas >=0.23
Requires-Dist: matplotlib >=3.3.0
Requires-Dist: loess >=2.1.2
Requires-Dist: scikit-learn >=1.2.2
Requires-Dist: tqdm <=4.62.3
Requires-Dist: igraph >=0.10.4
Requires-Dist: pynndescent >=0.5.7
Requires-Dist: hnswlib >=0.6.2
